mini_swe_agent-1.17.5.dist-info/licenses/LICENSE.md
minisweagent/__init__.py
minisweagent/__main__.py
minisweagent/py.typed
minisweagent/agents/__init__.py
minisweagent/agents/default.py
minisweagent/agents/interactive.py
minisweagent/agents/interactive_textual.py
minisweagent/config/README.md
minisweagent/config/__init__.py
minisweagent/config/default.yaml
minisweagent/config/github_issue.yaml
minisweagent/config/mini.tcss
minisweagent/config/mini.yaml
minisweagent/config/extra/__init__.py
minisweagent/config/extra/swebench.yaml
minisweagent/config/extra/swebench_roulette.yaml
minisweagent/config/extra/swebench_xml.yaml
minisweagent/environments/__init__.py
minisweagent/environments/docker.py
minisweagent/environments/local.py
minisweagent/environments/singularity.py
minisweagent/environments/extra/__init__.py
minisweagent/environments/extra/bubblewrap.py
minisweagent/environments/extra/swerex_docker.py
minisweagent/models/__init__.py
minisweagent/models/anthropic.py
minisweagent/models/litellm_model.py
minisweagent/models/litellm_response_api_model.py
minisweagent/models/openrouter_model.py
minisweagent/models/portkey_model.py
minisweagent/models/portkey_response_api_model.py
minisweagent/models/requesty_model.py
minisweagent/models/test_models.py
minisweagent/models/extra/__init__.py
minisweagent/models/extra/roulette.py
minisweagent/models/utils/__init__.py
minisweagent/models/utils/cache_control.py
minisweagent/models/utils/key_per_thread.py
minisweagent/models/utils/openai_utils.py
minisweagent/run/__init__.py
minisweagent/run/github_issue.py
minisweagent/run/hello_world.py
minisweagent/run/inspector.py
minisweagent/run/mini.py
minisweagent/run/mini_extra.py
minisweagent/run/extra/__init__.py
minisweagent/run/extra/config.py
minisweagent/run/extra/swebench.py
minisweagent/run/extra/swebench_single.py
minisweagent/run/extra/utils/__init__.py
minisweagent/run/extra/utils/batch_progress.py
minisweagent/run/utils/__init__.py
minisweagent/run/utils/save.py
minisweagent/utils/__init__.py
minisweagent/utils/log.py
mini_swe_agent-1.17.5.dist-info/METADATA
mini_swe_agent-1.17.5.dist-info/WHEEL
mini_swe_agent-1.17.5.dist-info/entry_points.txt
mini_swe_agent-1.17.5.dist-info/top_level.txt
mini_swe_agent-1.17.5.dist-info/RECORD
